Cipher/__init__.py
Cipher/cipher.py
Cipher/create_cipher_csv.py
cipherpy-0.1.dist-info/METADATA
cipherpy-0.1.dist-info/WHEEL
cipherpy-0.1.dist-info/top_level.txt
cipherpy-0.1.dist-info/RECORD
